{
  "_comment": "Manual type definitions for types that cannot be auto-extracted from CommonLibSSE headers. Used by parse_commonlib_types.py to supplement generated import scripts and embed a C prelude in CommonLibGhidra.py for signature parsing.",

  "typedefs": {
    "FormID":        { "base": "u32", "comment": "RE::FormID = std::uint32_t" },
    "ObjectRefHandle": { "base": "u32", "comment": "BSPointerHandle<TESObjectREFR> — internally a uint32_t handle" },
    "ActorHandle":   { "base": "u32", "comment": "BSPointerHandle<Actor> — internally a uint32_t handle" },
    "RefHandle":     { "base": "u32", "comment": "Generic BSPointerHandle — internally a uint32_t handle" },
    "VMHandle":      { "base": "u64", "comment": "RE::VMHandle = std::uint64_t" },
    "UPInt":         { "base": "u64", "comment": "GFx UPInt = size_t (8 bytes on x64)" },
    "hkpShapeKey":   { "base": "u32", "comment": "Havok shape key = uint32_t" },
    "va_list":       { "base": "u64", "comment": "MSVC x64 va_list = char * (8 bytes)" },
    "char16_t":      { "base": "u16", "comment": "C11 char16_t = uint16_t on MSVC x64" }
  },

  "enums": {
    "EffectArchetype": {
      "size": 4,
      "comment": "EffectArchetypes::ArchetypeID",
      "values": {
        "kNone": -1, "kValueModifier": 0, "kScript": 1, "kDispel": 2,
        "kCureDisease": 3, "kAbsorb": 4, "kDualValueModifier": 5,
        "kCalm": 6, "kDemoralize": 7, "kFrenzy": 8, "kDisarm": 9,
        "kCommandSummoned": 10, "kInvisibility": 11, "kLight": 12,
        "kDarkness": 13, "kNightEye": 14, "kLock": 15, "kOpen": 16,
        "kBoundWeapon": 17, "kSummonCreature": 18, "kDetectLife": 19,
        "kTelekinesis": 20, "kParalysis": 21, "kReanimate": 22,
        "kSoulTrap": 23, "kTurnUndead": 24, "kGuide": 25,
        "kWerewolfFeed": 26, "kCureParalysis": 27, "kCureAddiction": 28,
        "kCurePoison": 29, "kConcussion": 30, "kValueAndParts": 31,
        "kAccumulateMagnitude": 32, "kStagger": 33, "kPeakValueModifier": 34,
        "kCloak": 35, "kWerewolf": 36, "kSlowTime": 37, "kRally": 38,
        "kEnhanceWeapon": 39, "kSpawnHazard": 40, "kEtherealize": 41,
        "kBanish": 42, "kSpawnScriptedRef": 43, "kDisguise": 44,
        "kGrabActor": 45, "kVampireLord": 46
      }
    },
    "InputContextID": {
      "size": 4,
      "comment": "UserEvents::INPUT_CONTEXT_ID (ControlMap::InputContextID)",
      "values": {
        "kGameplay": 0, "kMenuMode": 1, "kConsole": 2, "kItemMenu": 3,
        "kInventory": 4, "kDebugText": 5, "kFavorites": 6, "kMap": 7,
        "kStats": 8, "kCursor": 9, "kBook": 10, "kDebugOverlay": 11,
        "kJournal": 12, "kTFCMode": 13, "kMapDebug": 14, "kLockpicking": 15,
        "kFavor": 16, "kTotal": 17, "kNone": 18
      }
    },
    "ITEM_REMOVE_REASON": {
      "size": 4,
      "comment": "enum class ITEM_REMOVE_REASON",
      "values": {
        "kRemove": 0, "kSteal": 1, "kSelling": 2,
        "kDropping": 3, "kStoreInContainer": 4, "kStoreInTeammate": 5
      }
    },
    "REGION_DATA_ID": {
      "size": 4,
      "comment": "enum class REGION_DATA_ID — forward-declared only, values unknown",
      "values": {}
    },
    "MATERIAL_ID": {
      "size": 4,
      "comment": "bhkShape material ID — values unknown",
      "values": {}
    },
    "LoadConstants": {
      "size": 4,
      "comment": "GFx LoadConstants flags — values unknown",
      "values": {}
    },
    "SpellType": {
      "size": 4,
      "comment": "MagicSystem::SpellType — values unknown",
      "values": {}
    },
    "CastingSource": {
      "size": 4,
      "comment": "MagicSystem::CastingSource — values unknown",
      "values": {}
    },
    "CannotCastReason": {
      "size": 4,
      "comment": "MagicSystem::CannotCastReason — values unknown",
      "values": {}
    },
    "ActorValue": {
      "size": 4,
      "comment": "RE::ActorValue — actor value enum, values omitted for brevity",
      "values": {}
    },
    "DEFAULT_OBJECT": {
      "size": 4,
      "comment": "BGSDefaultObjectManager::DEFAULT_OBJECT — values unknown",
      "values": {}
    },
    "SOUND_LEVEL": {
      "size": 4,
      "comment": "SOUND_LEVEL enum — values unknown",
      "values": {}
    },
    "ErrorCode": {
      "size": 4,
      "comment": "BSModelDB::ErrorCode — values unknown",
      "values": {}
    },
    "ACTOR_LOS_LOCATION": {
      "size": 4,
      "comment": "Actor line-of-sight location enum — values unknown",
      "values": {}
    },
    "ACTOR_VALUE_MODIFIER": {
      "size": 4,
      "comment": "Actor value modifier enum — values unknown",
      "values": {}
    },
    "FormType": {
      "size": 1,
      "comment": "RE::FormType — 1-byte enum for TESForm type IDs",
      "values": {}
    },
    "UI_MESSAGE_TYPE": {
      "size": 4,
      "comment": "UI_MESSAGE_TYPE enum — values unknown",
      "values": {}
    }
  },

  "opaques": {
    "BSFixedString":                 "detail::BSFixedString<char> template instantiation",
    "TintMask":                      "Forward-declared only",
    "IAIWorldLocation":              "Abstract AI world location — forward-declared only",
    "AIWorldLocationContext":        "AI world location context — forward-declared only",
    "IDebugText":                    "Debug text interface — forward-declared only",
    "NiVisibleArray":                "NiVisibleArray — forward-declared only",
    "TrespassPackage":               "Actor trespass package — forward-declared only",
    "CombatProjectileAimController": "Forward-declared only",
    "BSPathingStreamWrite":          "Forward-declared only",
    "BSPathingStreamRead":           "Forward-declared only",
    "hkStatisticsCollector":         "Havok statistics collector — forward-declared only",
    "hkaChunkCache":                 "Havok animation chunk cache — forward-declared only",
    "hkClass":                       "Havok class descriptor — forward-declared only",
    "hkpShapeRayCastInput":          "Havok shape ray cast input",
    "hkpShapeRayCastOutput":         "Havok shape ray cast output",
    "hkpShapeRayBundleCastInput":    "Havok shape ray bundle cast input",
    "hkpShapeRayBundleCastOutput":   "Havok shape ray bundle cast output",
    "hkpShapeModifier":              "Havok shape modifier",
    "hkpCdBodyPairCollector":        "Havok collision body pair collector",
    "hkpCollisionInput":             "Havok collision input",
    "hkpSimpleConstraintContactMgr": "Havok simple constraint contact manager",
    "hkAabbUint32":                  "Havok AABB uint32 type",
    "hkbContext":                    "Havok behavior context",
    "hkbClipGenerator":              "Havok behavior clip generator",
    "BSSynchronizedClipGenerator":   "Forward-declared only",
    "CollisionEntry":                "hkpCharacterRigidBodyListener collision entry",
    "CheckTargetArgs":               "ActiveEffectFactory check target args",
    "IUIMessageData":                "UI message data interface",
    "GFxMovieDef":                   "GFx movie definition",
    "GFxValue":                      "GFx value type",
    "ObjectInterface":               "GFx object interface",
    "RendererInitOSData":             "Renderer OS init data",
    "ApplicationWindowProperties":   "Application window properties",
    "SourceActionMap":               "Source action map",
    "IFunctionArguments":            "VM function arguments interface",
    "ISendEventFilter":              "VM send event filter interface",
    "TrapData":                      "Actor trap data",
    "TrapEntry":                     "Actor trap entry",
    "TargetEntry":                   "Actor target entry",
    "Location":                      "BSArchive loose file stream location",
    "ArgsType":                      "BSModelDB args type",
    "hkpCharacterRigidBody":         "Havok character rigid body",
    "hkpCharacterRigidBodyListener": "Havok character rigid body listener",
    "HWND":                          "Windows HWND (opaque handle pointer)",
    "NiAVObject":                    "Gamebryo/NiRTTI scene graph node base",
    "NiPoint3":                      "Gamebryo 3D float vector (x, y, z)",
    "NiColorA":                      "Gamebryo RGBA color (r, g, b, a floats)",
    "BSRenderPass":                  "BSRenderPass render submission record",
    "BSShaderProperty":              "BSShaderProperty material/shader property",
    "BSLight":                       "BSLight scene light",
    "BSGeometry":                    "BSGeometry renderable geometry node",
    "BSShader":                      "BSShader shader object",
    "BSAnimNoteReceiver":            "BSAnimNoteReceiver animation note callback",
    "BShkbAnimationGraph":           "BShkbAnimationGraph Havok behavior graph wrapper",
    "IAnimationGraphManagerHolder":  "IAnimationGraphManagerHolder animation graph owner interface",
    "BGSSoundDescriptorForm":        "BGSSoundDescriptorForm sound descriptor form",
    "BGSDecalNode":                  "BGSDecalNode decal scene node",
    "BSDynamicTriShape":             "BSDynamicTriShape dynamic triangle mesh",
    "BGSImpactManager":              "BGSImpactManager impact effect manager singleton",
    "BGSImpactDataSet":              "BGSImpactDataSet impact data set form",
    "BGSNumericIDIndex":             "BGSNumericIDIndex numeric form ID index",
    "BGSSaveLoadGame":               "BGSSaveLoadGame save/load manager",
    "BGSPrimitive":                  "BGSPrimitive collision primitive form",
    "TESHavokUtilities":             "TESHavokUtilities Havok scene utility singleton",
    "TESRegionData":                 "TESRegionData region data base class",
    "TESRegionDataGrass":            "TESRegionDataGrass region grass data",
    "TESRegionDataObjects":          "TESRegionDataObjects region object data",
    "TESRegionDataManager":          "TESRegionDataManager region data manager",
    "TESIdleForm":                   "TESIdleForm idle animation form",
    "ExtraDataList":                 "ExtraDataList extra data linked list on a form/ref",
    "InventoryEntryData":            "InventoryEntryData inventory item entry",
    "MagicItem":                     "MagicItem base class for spells/enchantments",
    "MagicCaster":                   "MagicCaster magic casting interface",
    "MagicSystem":                   "MagicSystem magic system namespace struct",
    "MagicUtilities":                "MagicUtilities magic utility singleton",
    "Effect":                        "Effect active magic effect descriptor",
    "ActiveEffectFactory":           "ActiveEffectFactory active effect factory singleton",
    "AIFormulas":                    "AIFormulas AI formula calculation utilities",
    "HitData":                       "HitData combat hit data structure",
    "MovementMessageActorCollision": "MovementMessageActorCollision movement collision message",
    "ActorMotionFeedbackOutput":     "ActorMotionFeedbackOutput actor motion feedback",
    "ControlMap":                    "ControlMap input control map singleton",
    "BSGamepadDevice":               "BSGamepadDevice gamepad input device",
    "SkyrimVM":                      "SkyrimVM Papyrus virtual machine singleton",
    "ConsoleLog":                    "ConsoleLog Papyrus/debug console log",
    "LooseFileStream":               "LooseFileStream loose file archive stream",
    "AnimationFileManagerSingleton": "AnimationFileManagerSingleton hkb animation file manager",
    "SendHUDMessage":                "SendHUDMessage HUD message sender",
    "SendUIMessage":                 "SendUIMessage UI message sender singleton",
    "PackageLocation":               "PackageLocation AI package target location",
    "NiDefaultAVObjectPalette":      "NiDefaultAVObjectPalette named NiAVObject lookup table",
    "BSScaleformExternalTexture":    "BSScaleformExternalTexture Scaleform external texture",
    "hkpCollidable":                 "Havok collidable shape wrapper",
    "hkVector4":                     "Havok SIMD 4-component float vector",
    "hkVector4Comparison":           "Havok SIMD vector comparison mask",
    "hkMoppBvTreeShapeBase":         "Havok MOPP bounding volume tree base",
    "hkpBoxShape":                   "Havok box collision shape",
    "hkpCapsuleShape":               "Havok capsule collision shape",
    "hkpCompressedMeshShape":        "Havok compressed mesh collision shape",
    "hkpConvexVerticesShape":        "Havok convex vertices collision shape",
    "hkpListShape":                  "Havok list/container collision shape",
    "hkpMoppBvTreeShape":            "Havok MOPP BV tree collision shape",
    "hkpSphereShape":                "Havok sphere collision shape",
    "hkpRigidBody":                  "Havok rigid body physics object",
    "bhkRigidBody":                  "Bethesda Havok rigid body wrapper",
    "bhkShape":                      "Bethesda Havok collision shape base",
    "CFilter":                       "Havok/Bethesda collision filter mask",
    "Result":                        "hkResult Havok operation result code",
    "hkpCdBody":                     "Havok collision detection body",
    "hkpRayHitCollector":            "Havok ray hit collector interface",
    "hkpSphere":                     "Havok sphere geometry descriptor",
    "hkSphere":                      "Havok sphere geometry descriptor (hkSphere variant)",
    "hkp3AxisSweep":                 "Havok 3-axis sweep broadphase",
    "hkpBroadPhaseHandle":           "Havok broadphase handle",
    "hkpCachingShapePhantom":        "Havok caching shape phantom",
    "hkpWorld":                      "Havok physics world",
    "hkpEntity":                     "Havok physics entity",
    "hkpPhantom":                    "Havok physics phantom",
    "hkpSimulationIsland":           "Havok simulation island",
    "hkpWorldObject":                "Havok physics world object base",
    "ahkpCharacterProxy":            "Bethesda Havok character proxy",
    "ahkpWorld":                     "Bethesda Havok world wrapper",
    "bhkCharacterStateClimbing":     "Bethesda Havok character climbing state",
    "hkbBehaviorGraph":              "Havok behavior graph",
    "hkbStateMachine":               "Havok behavior state machine",
    "hkQsTransform":                 "Havok quaternion-scale transform",
    "hkaAnimation":                  "Havok animation base",
    "hkaAnimationControl":           "Havok animation control base",
    "hkaDefaultAnimationControl":    "Havok default animation control",
    "NiCamera":                      "Gamebryo camera scene node",
    "NiMatrix3":                     "Gamebryo 3x3 rotation matrix",
    "BSCullingProcess":              "BSCullingProcess scene culling pass",
    "BSParabolicCullingProcess":     "BSParabolicCullingProcess parabolic culling pass",
    "NiBackToFrontAccumulator":      "Gamebryo back-to-front sort accumulator",
    "BSString":                      "BSString managed string type",
    "BSStream":                      "BSStream serialization stream",
    "ObjectBindPolicy":              "ObjectBindPolicy VM object binding policy",
    "ProjectileHandle":              "BSPointerHandle<Projectile> handle",
    "LaunchData":                    "Projectile launch data",
    "BSSoundHandle":                 "BSSoundHandle audio instance handle",
    "TESFile":                       "TESFile plugin/ESP/ESM file object",
    "TESDescription":                "TESDescription form description string",
    "TaskQueueInterface":            "TaskQueueInterface background task queue",
    "SpellItem":                     "SpellItem spell form",
    "BSPathingRequest":              "BSPathingRequest AI pathing request"
  }
}
